sage_dev_toolkit/__init__.py
sage_dev_toolkit/cli/__init__.py
sage_dev_toolkit/cli/main.py
sage_dev_toolkit/core/__init__.py
sage_dev_toolkit/core/config.py
sage_dev_toolkit/core/exceptions.py
sage_dev_toolkit/core/toolkit.py
sage_dev_toolkit/tools/__init__.py
sage_dev_toolkit/tools/class_dependency_checker.py
sage_dev_toolkit/tools/commercial_package_manager.py
sage_dev_toolkit/tools/dependency_analyzer.py
sage_dev_toolkit/tools/enhanced_package_manager.py
sage_dev_toolkit/tools/enhanced_test_runner.py
sage_dev_toolkit/tools/import_path_fixer.py
sage_dev_toolkit/tools/one_click_setup.py
sage_dev_toolkit/tools/sage_home_manager.py
sage_dev_toolkit/tools/vscode_path_manager.py
sage_dev_toolkit/utils/__init__.py
sage_dev_toolkit/utils/sage_home.py
sage_dev_toolkit/utils/sage_home_manager.py
intsage_dev_toolkit-1.0.0.dist-info/METADATA
intsage_dev_toolkit-1.0.0.dist-info/WHEEL
intsage_dev_toolkit-1.0.0.dist-info/entry_points.txt
intsage_dev_toolkit-1.0.0.dist-info/top_level.txt
intsage_dev_toolkit-1.0.0.dist-info/RECORD
