Metadata-Version: 2.4
Name: intsage-dev-toolkit
Version: 1.0.0
Summary: SAGE Framework Development Toolkit - Unified development tools for SAGE project
Author-email: IntelliStream Team <intellistream@outlook.com>
License: MIT
Project-URL: Homepage, https://github.com/intellistream/SAGE
Project-URL: Repository, https://github.com/intellistream/SAGE.git
Project-URL: Documentation, https://intellistream.github.io/SAGE-Pub/
Project-URL: Issues, https://github.com/intellistream/SAGE/issues
Keywords: formatting,framework,intellistream,ai,development,utilities,testing,data,tools,sage,ml,linting,cli
Classifier: Development Status :: 4 - Beta
Classifier: Intended Audience :: Developers
Classifier: Intended Audience :: Science/Research
Classifier: License :: OSI Approved :: MIT License
Classifier: Operating System :: OS Independent
Classifier: Programming Language :: Python :: 3
Classifier: Programming Language :: Python :: 3.10
Classifier: Programming Language :: Python :: 3.11
Classifier: Programming Language :: Python :: 3.12
Classifier: Topic :: Scientific/Engineering :: Artificial Intelligence
Classifier: Topic :: Software Development :: Libraries :: Python Modules
Classifier: Topic :: System :: Distributed Computing
Requires-Python: >=3.10
Requires-Dist: pyyaml==6.0.2
Requires-Dist: typer==0.16.0
Requires-Dist: rich==14.1.0
Requires-Dist: jinja2==3.1.6
Requires-Dist: pytest==8.4.1
Requires-Dist: pytest-asyncio==1.1.0
Requires-Dist: pytest-cov==6.2.1
Requires-Dist: pytest-benchmark==5.1.0
Requires-Dist: gitpython==3.1.45
Requires-Dist: packaging>=21.0
Requires-Dist: tomli>=2.0.0
Requires-Dist: tomli-w>=1.0.0
Requires-Dist: psutil==6.1.0
Requires-Dist: pathspec==0.12.1
Requires-Dist: pandas==2.3.1
Requires-Dist: networkx==3.4.2
Provides-Extra: dev
Requires-Dist: black>=23.0.0; extra == "dev"
Requires-Dist: isort>=5.12.0; extra == "dev"
Requires-Dist: mypy>=1.0.0; extra == "dev"
Requires-Dist: ruff>=0.1.0; extra == "dev"
Requires-Dist: pre-commit>=3.0.0; extra == "dev"
Provides-Extra: web
Requires-Dist: fastapi>=0.100.0; extra == "web"
Requires-Dist: uvicorn>=0.23.0; extra == "web"
Requires-Dist: websockets>=11.0; extra == "web"
Provides-Extra: docs
Requires-Dist: sphinx>=7.0.0; extra == "docs"
Requires-Dist: sphinx-rtd-theme>=1.3.0; extra == "docs"
Requires-Dist: myst-parser>=2.0.0; extra == "docs"
